{"cameraMode":{"drawMode":0,"name":"Shaded","section":"Shading Mode"},"sceneLighting":true,"audioPlay":false,"sceneViewState":{"m_AlwaysRefresh":false,"showFog":true,"showSkybox":true,"showFlares":true,"showImageEffects":true,"showParticleSystems":true,"showVisualEffectGraphs":true,"m_FxEnabled":true},"in2DMode":false,"pivot":{"x":32.78302001953125,"y":7.189481735229492,"z":989.1171875},"rotation":{"x":-0.00017653587565291673,"y":-0.9997702836990356,"z":-0.001189812901429832,"w":0.026777278631925584},"size":5.767870903015137,"orthographic":false}